oauth_emailbackend/__init__.py
oauth_emailbackend/admin.py
oauth_emailbackend/apps.py
oauth_emailbackend/backends.py
oauth_emailbackend/forms.py
oauth_emailbackend/models.py
oauth_emailbackend/tasks.py
oauth_emailbackend/test.html
oauth_emailbackend/tests.py
oauth_emailbackend/urls.py
oauth_emailbackend/utils.py
oauth_emailbackend/views.py
oauth_emailbackend/management/__init__.py
oauth_emailbackend/management/commands/__init__.py
oauth_emailbackend/migrations/0001_initial.py
oauth_emailbackend/migrations/__init__.py
oauth_emailbackend/providers/__init__.py
oauth_emailbackend/providers/gmail.py
oauth_emailbackend/templates/admin/oauth_emailbackend/emailclient/change_form.html
oauth_emailbackend/templates/oauth_emailbackend/callback.html
django_oauth_emailbackend-0.1.6.dist-info/LICENSE
django_oauth_emailbackend-0.1.6.dist-info/METADATA
django_oauth_emailbackend-0.1.6.dist-info/WHEEL
django_oauth_emailbackend-0.1.6.dist-info/top_level.txt
django_oauth_emailbackend-0.1.6.dist-info/RECORD
