Metadata-Version: 2.1
Name: django-oauth-emailbackend
Version: 0.1.6
Summary: Django emailbackend that using OAuth Gmail API or SMTP server.
Author-email: Sun-Yeon Lee <odop@youhasoft.com>
Project-URL: Homepage, https://github.com/youhasoft/django-oauth-emailbackend
Project-URL: Issues, https://github.com/youhasoft/django-oauth-emailbackend/issues
Classifier: Development Status :: 3 - Alpha
Classifier: Programming Language :: Python :: 3
Classifier: Programming Language :: Python :: 3.9
Classifier: Programming Language :: Python :: 3.10
Classifier: License :: OSI Approved :: MIT License
Classifier: Operating System :: OS Independent
Classifier: Framework :: Django
Classifier: Framework :: Django :: 3.2
Classifier: Framework :: Django :: 4.0
Classifier: Framework :: Django :: 5.0
Requires-Python: >=3.9
License-File: LICENSE
Requires-Dist: Django >3.2.8
Requires-Dist: celery >5.2
Requires-Dist: google-api-core
Requires-Dist: google-api-python-client
Requires-Dist: google-auth
Requires-Dist: google-auth-oauthlib
Requires-Dist: google-auth-httplib2
